myimage/__init__.py
myimage/common.py
myimage/settings.py
myimage/upload/__init__.py
myimage/upload/ali_oss.py
myimage/upload/ali_oss_cmd.py
myimage/upload/qiniuyun.py
myimage/upload/sm_ms.py
tests/__init__.py
tests/test_ali_oss.py
myimage-0.1.1.dist-info/LICENCE
myimage-0.1.1.dist-info/METADATA
myimage-0.1.1.dist-info/WHEEL
myimage-0.1.1.dist-info/top_level.txt
myimage-0.1.1.dist-info/RECORD
