Metadata-Version: 2.1
Name: myimage
Version: 0.1.1
Summary: A handful module for uploading local image and then get the path from specific server, especially good for those writing markdown journals.
Home-page: https://github.com/MarkShawn2020/myimage
Author: MarkShawn2020
Author-email: shawninjuly@gmail.com
License: UNKNOWN
Platform: UNKNOWN
Classifier: Programming Language :: Python :: 3
Classifier: License :: OSI Approved :: MIT License
Classifier: Operating System :: OS Independent
Requires-Python: >=3.5
Requires-Dist: requests
Requires-Dist: qiniu
